{
"作者":"凯哥",
"站名":"优狐视频",
"主页url":"https://yhsp778.com/",
//发布页https://youhushipin.github.io/https://youhu.gitbook.io
//"请求头":"Mozilla/5.0 (Linux; Android 12; CPH2199) AppleWebKit/537.36 (KHTML, like Gecko) Chrome/107.0.0.0 Mobile Safari/537.36",
"cookie":"",
"热门推荐":"1",
"直接播放":"0",
"二次截取":"id=\"list_videos_common_videos_list_items\">&&<div class=\"pagination\"",
"数组":"<a&&data-webp=",
"图片":"data-original=\"&&\"",
"标题":"",
"链接":"",
"链接后缀":"",
"副标题":"",
"搜索url":"https://yhsp778.com/search/{wd}/?mode=async&function=get_block&block_id=list_videos_videos_list_search_result&category_ids=&sort_by=&from_videos={pg}",
"搜索模式": "1",
"搜索二次截取": "id=\"list_videos_videos_list_search_result_items\">&&<div class=\"pagination\"",
"搜索数组": "<a&&data-webp=",
"搜索图片": "data-original=\"&&\"",
"搜索标题": "",
"搜索链接": "",
"搜索链接后缀":"",

//"线路二次截取":"<ul class=\"nav nav-tabs  dpplay pull-right\">&&</ul>",
"播放二次截取":"<div class=\"player-holder\">&&</div>",
//"线路数组":"<div class=\"stui-vodlist__head\">&&</div>",
"播放数组":"<div class=\"no-player\"&&您今日观看",
"状态":"更新：&&</span>",
"导演":"导演：&&</p>",
"主演":"主演：&&</p>",
"简介":"简介：&&</span>",
"播放列表":"<img&&message",
"播放标题":"alt=\"&&\"",
"播放链接":"https://hls.163cdns.com:2306/contents/videos/+src=\"/contents/videos_screenshots&&preview",
"播放链接后缀":"<link href=\"https://www.youhu.com/v/&&\"",
//"嗅探词":".m3u8?#.mp4#.m3u8",
//"过滤词":"url=#?v=https",
"播放请求头":"",
//"免嗅":"0",
"分类":"91视频$91porn#国产自拍$guo-chan-zi-pai#国产主播$zhong-guo-zhu-bo#偷拍视频$tou-pai-shi-pin#国产精品$guo-chan-jing-pin#欧美$ou-mei#国产传媒$guo-chan-chuan-mei",
"分类url":"https://yhsp778.com/categories/{cateId}/?mode=async&function=get_block&block_id=list_videos_common_videos_list&sort_by=post_date&from={catePg}",
 "筛选":{
"91porn":[
  {"key":"cateId","name":"类型","value":[
  {"n":"全部","v":""},
  {"n":"日本无码","v":"ri-ben-wu-ma"},
  {"n":"国产主播","v":"guo-chan-zhu-bo"},
  {"n":"国产原创","v":"guo-chan-yuan-chuang"},
  {"n":"三级综艺","v":"san-ji-zong-yi"},
  {"n":"人妖视频","v":"ren-yao-shi-pin"},
  {"n":"国产探花","v":"guo-chan-tan-hua"},
  {"n":"国产网曝","v":"guo-chan-wang-pu"},
  {"n":"华语AV","v":"hua-yu-av"},
  {"n":"國產品牌新資源","v":"guo-chan-pin-pai-xin-zi-yuan2"},
  {"n":"日韩无码","v":"ri-han-wu-ma"},
  {"n":"mywife","v":"scute-mywife"},
  {"n":"亞洲SM","v":"ya-zhou-sm"},
  {"n":"日本高清","v":"ri-ben-gao-qing"},
  {"n":"國產直播","v":"guo-chan-zhi-bo"},
  {"n":"日韩自拍","v":"ri-han-zi-pai"}]}],
  
"guo-chan-zi-pai":[
 {"key":"cateId","name":"类型","value":[
  {"n":"全部","v":""},
  {"n":"欧美自拍","v":"ou-mei-zi-pai"},
  {"n":"国产裸聊","v":"guo-chan-luo-liao"},
  {"n":"三级","v":"san-ji"},
  {"n":"精品偷拍","v":"jing-pin-tou-pai"}
  ]}],
  
"zhong-guo-zhu-bo":[
  {"key":"cateId","name":"类型","value":[
  {"n":"全部","v":""},
  {"n":"国产偷拍","v":"guo-chan-tou-pai"},
  {"n":"摄像头","v":"dao-she"},
  {"n":"主播网红","v":"zhu-bo-wang-hong"}]}],
  
"tou-pai-shi-pin":[
  {"key":"cateId","name":"类型","value":[
  {"n":"全部","v":""},
  {"n":"SM调教","v":"sm-tiao-jiao"},
  {"n":"自慰合集","v":"zi-wei-he-ji"},
  {"n":"3P群交","v":"3p-qun-jiao"}]}]}
}
